{"labelsByUnit":{"0":["noise"],"1":["noise"],"10":["noise"],"103":["noise"],"107":["noise"],"112":["noise"],"116":["noise"],"129":["noise"],"13":["noise"],"136":["noise"],"137":["noise"],"138":["noise"],"140":["noise"],"141":["noise"],"15":["noise"],"20":["noise"],"25":["noise"],"38":["noise"],"48":["noise"],"50":["noise"],"52":["noise"],"53":["noise"],"56":["noise"],"57":["noise"],"58":["noise"],"59":["noise"],"6":["noise"],"62":["noise"],"65":["noise"],"66":["noise"],"67":["noise"],"68":["noise"],"69":["noise"],"7":["noise"],"71":["noise"],"72":["noise"],"73":["noise"],"90":["noise"],"99":["noise"]}}